paddock/__init__.py
paddock/__version__.py
paddock/_client.py
paddock/_dataclasses.py
paddock/_marshmallow.py
paddock/_response.py
paddock/_util.py
paddock/constants.py
paddock/models/__init__.py
paddock/models/_cars.py
paddock/models/_common.py
paddock/models/_season.py
paddock/models/_tracks.py
paddock-0.1.0b6.dist-info/METADATA
paddock-0.1.0b6.dist-info/WHEEL
paddock-0.1.0b6.dist-info/top_level.txt
paddock-0.1.0b6.dist-info/RECORD
